datadome_asgi/__init__.py
datadome_asgi/middleware.py
datadome_asgi-1.0.0.dist-info/licenses/LICENSE
datadome_asgi-1.0.0.dist-info/METADATA
datadome_asgi-1.0.0.dist-info/WHEEL
datadome_asgi-1.0.0.dist-info/top_level.txt
datadome_asgi-1.0.0.dist-info/RECORD
