Metadata-Version: 2.4
Name: datadome-asgi
Version: 1.0.0
Summary: DataDome Bot Protect middleware for ASGI 3.0 applications
Author-email: DataDome <support@datadome.co>
Requires-Python: >=3.10
License-File: LICENSE
Requires-Dist: httpx>=0.28.1
Provides-Extra: dev
Requires-Dist: ruff>=0.14.6; extra == "dev"
Dynamic: license-file
